leeger/__init__.py
leeger/_version.py
leeger/calculator/__init__.py
leeger/calculator/all_time_calculator/AWALAllTimeCalculator.py
leeger/calculator/all_time_calculator/GameOutcomeAllTimeCalculator.py
leeger/calculator/all_time_calculator/PlusMinusAllTimeCalculator.py
leeger/calculator/all_time_calculator/PointsScoredAllTimeCalculator.py
leeger/calculator/all_time_calculator/SSLAllTimeCalculator.py
leeger/calculator/all_time_calculator/ScoringShareAllTimeCalculator.py
leeger/calculator/all_time_calculator/ScoringStandardDeviationAllTimeCalculator.py
leeger/calculator/all_time_calculator/SingleScoreAllTimeCalculator.py
leeger/calculator/all_time_calculator/SmartWinsAllTimeCalculator.py
leeger/calculator/all_time_calculator/TeamSummaryAllTimeCalculator.py
leeger/calculator/all_time_calculator/__init__.py
leeger/calculator/parent/AllTimeCalculator.py
leeger/calculator/parent/YearCalculator.py
leeger/calculator/parent/__init__.py
leeger/calculator/year_calculator/AWALYearCalculator.py
leeger/calculator/year_calculator/GameOutcomeYearCalculator.py
leeger/calculator/year_calculator/PlusMinusYearCalculator.py
leeger/calculator/year_calculator/PointsScoredYearCalculator.py
leeger/calculator/year_calculator/SSLYearCalculator.py
leeger/calculator/year_calculator/ScoringShareYearCalculator.py
leeger/calculator/year_calculator/ScoringStandardDeviationYearCalculator.py
leeger/calculator/year_calculator/SingleScoreYearCalculator.py
leeger/calculator/year_calculator/SmartWinsYearCalculator.py
leeger/calculator/year_calculator/TeamSummaryYearCalculator.py
leeger/calculator/year_calculator/__init__.py
leeger/decorator/__init__.py
leeger/decorator/validators.py
leeger/enum/MatchupType.py
leeger/enum/__init__.py
leeger/exception/DoesNotExistException.py
leeger/exception/InvalidDivisionFormatException.py
leeger/exception/InvalidFilterException.py
leeger/exception/InvalidLeagueFormatException.py
leeger/exception/InvalidMatchupFormatException.py
leeger-2.7.0.dist-info/LICENSE
leeger-2.7.0.dist-info/METADATA
leeger-2.7.0.dist-info/WHEEL
leeger-2.7.0.dist-info/top_level.txt
leeger-2.7.0.dist-info/RECORD
