Metadata-Version: 2.1
Name: leeger
Version: 2.7.0
Summary: Instant stats for any fantasy football league.
Home-page: https://github.com/joeyagreco/leeger
Author: Joey Greco
Author-email: joeyagreco@gmail.com
License: MIT
Keywords: nfl statistics stats football espn yahoo sleeper myfantasyleague,fleaflicker
Requires-Python: >=3.10
License-File: LICENSE
Requires-Dist: espn_api~=0.43.0
Requires-Dist: fleaflicker~=1.0.0
Requires-Dist: numpy~=1.24.4
Requires-Dist: openpyxl~=3.1.2
Requires-Dist: pymfl~=1.0.2
Requires-Dist: setuptools~=66.1.1
Requires-Dist: sleeper~=1.6.0
Requires-Dist: yahoofantasy~=1.4.2
